FRUIT.py
FRUITPy-1.0.0.dist-info/METADATA
FRUITPy-1.0.0.dist-info/WHEEL
FRUITPy-1.0.0.dist-info/top_level.txt
FRUITPy-1.0.0.dist-info/RECORD
